setup.py
gc_python_utils/__init__.py
gc_python_utils.egg-info/PKG-INFO
gc_python_utils.egg-info/SOURCES.txt
gc_python_utils.egg-info/dependency_links.txt
gc_python_utils.egg-info/not-zip-safe
gc_python_utils.egg-info/top_level.txt