Metadata-Version: 1.0
Name: gc-python-utils
Version: 0.0.1
Summary: GameChanger general python utilities
Home-page: https://github.com/gamechanger/python-utils
Author: GameChanger
Author-email: jordan.singleton@gamechanger.io
License: UNKNOWN
Platform: UNKNOWN
